<?xml version="1.0" encoding="UTF-8"?>
<soap:Envelope xmlns:soap="http://www.w3.org/2003/05/soap-envelope">
<soap:Header>
<Header>
<SentAt>
<Date>
<Year>2011</Year>
<Month>04</Month>
<Day>04</Day>
</Date>
<Time>00:12:00</Time>
</SentAt>
<Transmitter>AC.AIRCFRA.1507</Transmitter>
<Receiver>DE.UNSY.TST</Receiver>
<Method>ESU</Method>
<MessageTP>
<CountryCode>DE</CountryCode>
<Procedure>ICS</Procedure>
<MessageName>ICSDeclarationAmendment</MessageName>
<Release>1.0.00</Release>
<Direction>FROM_CUSTOMER</Direction>
</MessageTP>
<CustomsExchange>
<Codemapping>
<Map>0</Map>
<MapFrom>DE</MapFrom>
<MapTo>DE</MapTo>
</Codemapping>
</CustomsExchange>
<MessageID>6071121774047399002805</MessageID>
</Header>
</soap:Header>
<soap:Body>
<ICSDeclarationAmendment>
<GoodsDeclaration>
<ReferenceNumber>6070350520037399002791</ReferenceNumber>
<ShipmentNumber>01465180264</ShipmentNumber>
<MRN>11DE587600032589I7</MRN>
<TotalNumberPositions>6</TotalNumberPositions>
<TotalNumberPackages>26</TotalNumberPackages>
<TotalGrossMass>315.0</TotalGrossMass>
<MeansOfTransportBorder>
<TransportMode>4</TransportMode>
</MeansOfTransportBorder>
<ConveyanceReference>AC844</ConveyanceReference>
<LoadingPlace>CAYYC</LoadingPlace>
<UnloadingPlace>DEFRA</UnloadingPlace>
<DeclarationTime>201104040012</DeclarationTime>
<DeclarationPlace>FRA</DeclarationPlace>
<ConsignorAddress>
<Address>
<Name>KUEHNE NAGEL INC</Name>
<Street>18900 8TH AVENUE SOUTH SUITE 1300</Street>
<City>SEA-TAC</City>
<PostalCode>98148</PostalCode>
<Country>US</Country>
<CountrySubEntity>WA</CountrySubEntity>
</Address>
</ConsignorAddress>
<ConsigneeAddress>
<Address>
<Name>KUEHNE   NAGEL AG   CO KG</Name>
<Street>CARGOCITY SUED GEB 554</Street>
<City>KELSTERBACH</City>
<PostalCode>65451</PostalCode>
<Country>DE</Country>
</Address>
</ConsigneeAddress>
<PersonLodgingSumaTIN>
<TIN>DE9008691</TIN>
</PersonLodgingSumaTIN>
<PersonLodgingSumaAddress>
<Address>
<Name>AIR CANADA</Name>
<Street>PO BOX 14000</Street>
<City>MONTREAL</City>
<PostalCode>H4Y 1H4</PostalCode>
<Country>CA</Country>
<CountrySubEntity>QC</CountrySubEntity>
</Address>
</PersonLodgingSumaAddress>
<PersonLodgingSumaContact>
<Clerk>AIR CANADA</Clerk>
<PhoneNumber>(514) 422 5000</PhoneNumber>
</PersonLodgingSumaContact>
<CustomsOfficeFirstEntry>DE005876</CustomsOfficeFirstEntry>
<DeclaredDateOfArrival>201104041120</DeclaredDateOfArrival>
<CountryOfRouting>US</CountryOfRouting>
<CountryOfRouting>CA</CountryOfRouting>
<CountryOfRouting>DE</CountryOfRouting>
<GoodsItem>
<ItemNumber>1</ItemNumber>
<Description>CIVIL AIRCRAFT PARTS</Description>
<GrossMass>8.0</GrossMass>
<LoadingPlace>CAYYC</LoadingPlace>
<UnloadingPlace>DEFRA</UnloadingPlace>
<Packages>
<Type>NE</Type>
<Number>5</Number>
</Packages>
<MeansOfTransportBorder>
<TransportMode>4</TransportMode>
</MeansOfTransportBorder>
<Document>
<Type>N703</Type>
<Reference>SEA47054082</Reference>
</Document>
</GoodsItem>
<GoodsItem>
<ItemNumber>2</ItemNumber>
<Description>CIVIL AIRCRAFT PARTS</Description>
<GrossMass>2.0</GrossMass>
<LoadingPlace>CAYYC</LoadingPlace>
<UnloadingPlace>DEFRA</UnloadingPlace>
<Packages>
<Type>NE</Type>
<Number>2</Number>
</Packages>
<MeansOfTransportBorder>
<TransportMode>4</TransportMode>
</MeansOfTransportBorder>
<Document>
<Type>N703</Type>
<Reference>SEA47054083</Reference>
</Document>
</GoodsItem>
<GoodsItem>
<ItemNumber>3</ItemNumber>
<Description>BLACK SCREW COVER CAPS W ADHESIVE</Description>
<GrossMass>30.0</GrossMass>
<LoadingPlace>CAYYC</LoadingPlace>
<UnloadingPlace>DEFRA</UnloadingPlace>
<Packages>
<Type>NE</Type>
<Number>2</Number>
</Packages>
<MeansOfTransportBorder>
<TransportMode>4</TransportMode>
</MeansOfTransportBorder>
<Document>
<Type>N703</Type>
<Reference>SEA47054096</Reference>
</Document>
</GoodsItem>
<GoodsItem>
<ItemNumber>4</ItemNumber>
<Description>MAPLE SCREW COVER CAPS W ADHESIVE</Description>
<GrossMass>9.0</GrossMass>
<LoadingPlace>CAYYC</LoadingPlace>
<UnloadingPlace>DEFRA</UnloadingPlace>
<Packages>
<Type>NE</Type>
<Number>1</Number>
</Packages>
<MeansOfTransportBorder>
<TransportMode>4</TransportMode>
</MeansOfTransportBorder>
<Document>
<Type>N703</Type>
<Reference>SEA47054095</Reference>
</Document>
</GoodsItem>
<GoodsItem>
<ItemNumber>5</ItemNumber>
<Description>SILVER SEAL SILICONE ERGO COMPUTER MOU</Description>
<GrossMass>32.0</GrossMass>
<LoadingPlace>CAYYC</LoadingPlace>
<UnloadingPlace>DEFRA</UnloadingPlace>
<Packages>
<Type>NE</Type>
<Number>3</Number>
</Packages>
<MeansOfTransportBorder>
<TransportMode>4</TransportMode>
</MeansOfTransportBorder>
<Document>
<Type>N703</Type>
<Reference>SEA47054094</Reference>
</Document>
</GoodsItem>
<GoodsItem>
<ItemNumber>6</ItemNumber>
<Description>DOUGH WORKING EQUIPMENT</Description>
<GrossMass>277.0</GrossMass>
<LoadingPlace>CAYYC</LoadingPlace>
<UnloadingPlace>DEFRA</UnloadingPlace>
<Packages>
<Type>NE</Type>
<Number>13</Number>
</Packages>
<MeansOfTransportBorder>
<TransportMode>4</TransportMode>
</MeansOfTransportBorder>
<Document>
<Type>N703</Type>
<Reference>SEA47054097</Reference>
</Document>
</GoodsItem>
</GoodsDeclaration>
</ICSDeclarationAmendment>
</soap:Body>
</soap:Envelope>
