<?xml version="1.0" encoding="UTF-8"?>
<soap:Envelope xmlns:soap="http://www.w3.org/2003/05/soap-envelope">
<soap:Header>
<KIDSHeader>
<SentAt>
<Date>
<Year>2013</Year>
<Month>4</Month>
<Day>22</Day>
</Date>
<Time>145111</Time>
<TimeZone>+0100</TimeZone>
</SentAt>
<Transmitter>DE.BDP.TST</Transmitter>
<Receiver>DE.BDP.TST</Receiver>
<Method>IMPORT</Method>
<MessageTP>
<CountryCode>DE</CountryCode>
<Procedure>IMPORT</Procedure>
<ProcedureSpecification>1</ProcedureSpecification>
<MessageName>ImportDeclaration</MessageName>
<Release>2.0.00</Release>
<Direction>FROM_CUSTOMER</Direction>
</MessageTP>
<CustomsExchange>
<Codemapping>
<Map>0</Map>
<MapFrom>DE</MapFrom>
<MapTo>DE</MapTo>
</Codemapping>
</CustomsExchange>
<MessageID>KE_IMP_TEST_BDP_01</MessageID>
</KIDSHeader>
</soap:Header>
<soap:Body>
<ImportDeclaration>
<GoodsDeclaration>
<ReferenceNumber>KE_IMP_TEST_BDP_01</ReferenceNumber>
<DeclarationPriorPresentation>N</DeclarationPriorPresentation>
<AgentRepresentationCode>BT002</AgentRepresentationCode>
<PreTaxDeductionCode>N</PreTaxDeductionCode>
<TransportInContainer>N</TransportInContainer>
<Business>
<BusinessTypeCode>11</BusinessTypeCode>
</Business>
<PlaceOfDeclaration>FRA</PlaceOfDeclaration>
<CustomsOfficeOfDeclaration>3302</CustomsOfficeOfDeclaration>
<Traders>
<DeclarantTIN>
<TIN>3076628</TIN>
<BO>0000</BO>
<VATNumber>DE129455643</VATNumber>
</DeclarantTIN>
<DeclarantAddress>
<Name>Sanyo Component Europe GmbH</Name>
<Street>Stahlgruberring</Street>
<HouseNumber>4</HouseNumber>
<City>MueNCHEN</City>
<PostalCode>81829</PostalCode>
<Country>DE</Country>
</DeclarantAddress>
<RepresentativeTIN>
<TIN>2614987</TIN>
<BO>0000</BO>
<CustomerID>DE.BDP.TST</CustomerID>
</RepresentativeTIN>
<RepresentativeAddress>
<Name>BDP Deutschland GmbH</Name>
<Street>Cargo City Sued Geb</Street>
<HouseNumber>111</HouseNumber>
<City>FRANKFURT AM MAIN</City>
<PostalCode>60549</PostalCode>
<Country>DE</Country>
</RepresentativeAddress>
<ConsignorAddress>
<Name>Sanyo Electric Co.,Ltd.</Name>
<Street>Keihan-Hondori</Street>
<HouseNumber>5-5</HouseNumber>
<City>OSAKA</City>
<PostalCode>570-8677</PostalCode>
<Country>JP</Country>
</ConsignorAddress>
<ConsigneeTIN>
<TIN>3076628</TIN>
<BO>0000</BO>
</ConsigneeTIN>
<ConsigneeAddress>
<Name>Sanyo Component Europe GmbH</Name>
<Street>Stahlgruberring</Street>
<HouseNumber>4</HouseNumber>
<City>MueNCHEN</City>
<PostalCode>81829</PostalCode>
<Country>DE</Country>
</ConsigneeAddress>
<CustomsValueDeclarantTIN>
<TIN>2614987</TIN>
<BO>0000</BO>
<CustomerID>1918</CustomerID>
</CustomsValueDeclarantTIN>
<CustomsValueDeclarantAddress>
<Name>BDP Deutschland GmbH</Name>
<Street>Cargo City Sued Geb</Street>
<HouseNumber>570</HouseNumber>
<City>FRANKFURT AM MAIN</City>
<PostalCode>60549</PostalCode>
<Country>DE</Country>
</CustomsValueDeclarantAddress>
</Traders>
<DispatchCountry>JP</DispatchCountry>
<ImporterLocation>00</ImporterLocation>
<DestinationFederalState>12</DestinationFederalState>
<CustomsStatus>AE003</CustomsStatus>
<PreviousDocument>
<Type>PD-Type</Type>
<Number>PD-Number</Number>
</PreviousDocument>
<MeansOfTransportBorder>
<TransportMode>BA017</TransportMode>
<TransportationType>AD021</TransportationType>
<TransportationCountry>DE</TransportationCountry>
</MeansOfTransportBorder>
<ContactPerson>
<Clerk>CKEIL</Clerk>
<Identity>CKEIL</Identity>
</ContactPerson>
<IncoTerms>
<Code>EXW</Code>
</IncoTerms>
<ManifestCompletion>
<RegistrationNumber>PD-RegistrationNumber</RegistrationNumber>
<ItemNumber>PD-RegistrationItemNumber</ItemNumber>
<NumberOfPieces>PD-Amount</NumberOfPieces>
<Custodian>
<TIN>TIN</TIN>
</Custodian>
<SpecificKey>
<Code>PD-Term1</Code>
<Number>PD-Term2</Number>
</SpecificKey>
</ManifestCompletion>
<GoodsItem>
<ItemNumber>1</ItemNumber>
<ProcedureCode>4000</ProcedureCode>
<Description>Battery Parts</Description>
<PlaceOfDeparture>OSA</PlaceOfDeparture>
<GrossMass>36000</GrossMass>
<Package>
<Quantity>3</Quantity>
<Type>CN172</Type>
</Package>
</GoodsItem>
</GoodsDeclaration>
</ImportDeclaration>
</soap:Body>
</soap:Envelope>
